GraphHandler.py
GraphHandler-0.1.3.dist-info/LICENSE
GraphHandler-0.1.3.dist-info/METADATA
GraphHandler-0.1.3.dist-info/WHEEL
GraphHandler-0.1.3.dist-info/top_level.txt
GraphHandler-0.1.3.dist-info/RECORD
