Metadata-Version: 2.1
Name: GraphHandler
Version: 0.1.3
Summary: Unofficial Facebook Graph API Handler
Author: Ambar Rizvi
Author-email: <brannstrom9911@gmail.com>
Keywords: python,facebook,graph api,social media,instagram,meta,meta api
Classifier: Development Status :: 2 - Pre-Alpha
Classifier: Intended Audience :: Developers
Classifier: Programming Language :: Python :: 3
Classifier: License :: OSI Approved :: MIT License
Classifier: Operating System :: Unix
Classifier: Operating System :: MacOS :: MacOS X
Classifier: Operating System :: Microsoft :: Windows
License-File: LICENSE
Requires-Dist: requests ==2.31.0
Requires-Dist: typing ==3.7.4.3
